vibe.py
vibe_chart.py-1.0.1.dist-info/LICENSE
vibe_chart.py-1.0.1.dist-info/METADATA
vibe_chart.py-1.0.1.dist-info/WHEEL
vibe_chart.py-1.0.1.dist-info/top_level.txt
vibe_chart.py-1.0.1.dist-info/RECORD
