Metadata-Version: 2.1
Name: vibe-chart.py
Version: 1.0.1
Summary: Python API for downloading Naver Vibe charts
Home-page: https://github.com/gold24park/vibe-chart.py
Author: Lou Park
Author-email: gold24park@gmail.com
License: MIT License
License-File: LICENSE
Requires-Dist: requests (>=2.28.2)
